MANIFEST.in
README.md
setup.py
autoit/__init__.py
autoit/autoit.py
autoit/control.py
autoit/process.py
autoit/win.py
autoit/lib/AutoItX3.dll
autoit/lib/AutoItX3_x64.dll
pyautoit_win64.egg-info/PKG-INFO
pyautoit_win64.egg-info/SOURCES.txt
pyautoit_win64.egg-info/dependency_links.txt
pyautoit_win64.egg-info/top_level.txt